conf/__init__.py
conf/reader.py
conf/parsers/__init__.py
conf/parsers/ini_parser.py
conf/parsers/json_parser.py
conf/parsers/yaml_parser.py
conf-0.4.0.dist-info/LICENSE
conf-0.4.0.dist-info/METADATA
conf-0.4.0.dist-info/WHEEL
conf-0.4.0.dist-info/top_level.txt
conf-0.4.0.dist-info/RECORD
