Metadata-Version: 2.1
Name: conf
Version: 0.4.0
Summary: Facilitates a convenient use of configuration files
Home-page: https://github.com/ramonhagenaars/conf
Author: Ramon Hagenaars
Author-email: ramon.hagenaars@gmail.com
License: UNKNOWN
Platform: UNKNOWN
Classifier: Programming Language :: Python :: 3
Classifier: Operating System :: OS Independent
Provides-Extra: yaml
Requires-Dist: PyYAML (>=5.1) ; extra == 'yaml'
